Workbook

Sheet Appendix 3
C3: Appendix 3 | O3: Selected Ratios
E5: Actual | G5: Projected | Q5: Actual | S5: Projected
E6: 2012 | G6: 2013 | H6: 2014 | I6: 2015 | J6: 2016 | K6: 2017 | Q6: 2012 | S6: 2013 | T6: 2014 | U6: 2015 | V6: 2016 | W6: 2017
C8: Sales | E8: 6234.1 | G8: 7792.6 | H8: 9351.2 | I8: 10753.8 | J8: 11829.2 | K8: 12420.7 | O8: Growth Rate in Sales | S8: =(G8-E8)/E8 -> 0.24999599 | T8: =(H8-G8)/G8 -> 0.20001027 | U8: =(I8-H8)/H8 -> 0.14999144 | V8: =(J8-I8)/I8 -> 0.10000186 | W8: =(K8-J8)/J8 -> 0.050003381
C9: COGS | E9: 4041.9 | G9: 4994.8 | H9: 5993.8 | I9: 6892.8 | J9: 7582.1 | K9: 7961.2 | O9: COGS % Sales | Q9: =E9/E8 -> 0.64835341 | S9: =G9/G8 -> 0.64096707 | T9: =H9/H8 -> 0.64096587 | U9: =I9/I8 -> 0.64096412 | V9: =J9/J8 -> 0.64096473 | W9: =K9/K8 -> 0.64096226
C10: Gross Margin | E10: =E8-E9 -> 2192.2 | G10: =G8-G9 -> 2797.8 | H10: =H8-H9 -> 3357.4 | I10: =I8-I9 -> 3861 | J10: =J8-J9 -> 4247.1 | K10: =K8-K9 -> 4459.5
C11: Gross Margin (%) | E11: =E10/E8 -> 0.35164659 | G11: =G10/G8 -> 0.35903293 | H11: =H10/H8 -> 0.35903413 | I11: =I10/I8 -> 0.35903588 | J11: =J10/J8 -> 0.35903527 | K11: =K10/K8 -> 0.35903774
C13: Marketing & Selling | E13: 1030.2 | G13: 1202 | H13: 1344.2 | I13: 1504.4 | J13: 1722.9 | K13: 1875 | O13: Marketing & Selling % Sales | Q13: =E13/E8 -> 0.1652524 | S13: =G13/G8 -> 0.1542489 | T13: =H13/H8 -> 0.14374626 | U13: =I13/I8 -> 0.13989473 | V13: =J13/J8 -> 0.14564806 | W13: =K13/K8 -> 0.15095768
C14: G&A Expenses | E14: 569 | G14: 660.2 | H14: 960 | I14: 1134.2 | J14: 1180.2 | K14: 1200 | O14: G&A Expenses % Sales | Q14: =E14/E8 -> 0.091272196 | S14: =G14/G8 -> 0.084721402 | T14: =H14/H8 -> 0.10266062 | U14: =I14/I8 -> 0.10546969 | V14: =J14/J8 -> 0.099770061 | W14: =K14/K8 -> 0.096612912
C15: EBITDA | E15: =E10-E13-E14 -> 593 | G15: =G10-G13-G14 -> 935.6 | H15: =H10-H13-H14 -> 1053.2 | I15: =I10-I13-I14 -> 1222.4 | J15: =J10-J13-J14 -> 1344 | K15: =K10-K13-K14 -> 1384.5
C16: EBITDA Margin (%) | E16: =E15/E8 -> 0.09512199 | G16: =G15/G8 -> 0.12006262 | H16: =H15/H8 -> 0.11262726 | I16: =I15/I8 -> 0.11367145 | J16: =J15/J8 -> 0.11361715 | K16: =K15/K8 -> 0.11146715
C18: Depreciation | E18: 156.4 | G18: 174.4 | H18: 190 | I18: 200 | J18: 220.5 | K18: 250
C19: EBT | E19: =E15-E18 -> 436.6 | G19: =G15-G18 -> 761.2 | H19: =H15-H18 -> 863.2 | I19: =I15-I18 -> 1022.4 | J19: =J15-J18 -> 1123.5 | K19: =K15-K18 -> 1134.5
C20: EBT Margin (%) | E20: =E19/E8 -> 0.070034167 | G20: =G19/G8 -> 0.097682417 | H20: =H19/H8 -> 0.092309008 | I20: =I19/I8 -> 0.095073369 | J20: =J19/J8 -> 0.094976837 | K20: =K19/K8 -> 0.091339458
C22: Taxes | E22: 172.5 | G22: 289.3 | H22: 328 | I22: 388.5 | J22: 426.9 | K22: 431.1 | O22: Effective Tax Rate | Q22: =E22/E19 -> 0.39509849 | S22: =G22/G19 -> 0.3800578 | T22: =H22/H19 -> 0.37998146 | U22: =I22/I19 -> 0.37998826 | V22: =J22/J19 -> 0.3799733 | W22: =K22/K19 -> 0.37999119
C23: Net Income | E23: =E19-E22 -> 264.1 | G23: =G19-G22 -> 471.9 | H23: =H19-H22 -> 535.2 | I23: =I19-I22 -> 633.9 | J23: =J19-J22 -> 696.6 | K23: =K19-K22 -> 703.4
C24: Return on Sales (%) | E24: =E23/E8 -> 0.042363773 | G24: =G23/G8 -> 0.060557452 | H24: =H23/H8 -> 0.057233296 | I24: =I23/I8 -> 0.058946605 | J24: =J23/J8 -> 0.058888175 | K24: =K23/K8 -> 0.056631269
C26: Operating Cash Flow | E26: =E23+E18 -> 420.5 | G26: =G23+G18 -> 646.3 | H26: =H23+H18 -> 725.2 | I26: =I23+I18 -> 833.9 | J26: =J23+J18 -> 917.1 | K26: =K23+K18 -> 953.4
C28: Change in NWC | E28: -170.4 | G28: -200 | H28: -210 | I28: -245 | J28: -260 | K28: -275 | O28: Growth Rate in NWC | S28: =(G28-E28)/E28 -> 0.17370892 | T28: =(H28-G28)/G28 -> 0.05 | U28: =(I28-H28)/H28 -> 0.16666667 | V28: =(J28-I28)/I28 -> 0.06122449 | W28: =(K28-J28)/J28 -> 0.057692308
C30: Change in Capex | E30: 0 | G30: -50 | H30: -50 | I30: -50 | J30: -50 | K30: -50 | O30: Capex % Depreciation | S30: =-G30/G18 -> 0.28669725 | T30: =-H30/H18 -> 0.26315789 | U30: =-I30/I18 -> 0.25 | V30: =-J30/J18 -> 0.22675737 | W30: =-K30/K18 -> 0.2
C32: Free Cash Flow | E32: =E26+E28+E30 -> 250.1 | G32: =G26+G28+G30 -> 396.3 | H32: =H26+H28+H30 -> 465.2 | I32: =I26+I28+I30 -> 538.9 | J32: =J26+J28+J30 -> 607.1 | K32: =K26+K28+K30 -> 628.4 | O32: Growth Rate in Free Cash Flow | S32: =(G32-E32)/E32 -> 0.58456617 | T32: =(H32-G32)/G32 -> 0.17385819 | U32: =(I32-H32)/H32 -> 0.15842648 | V32: =(J32-I32)/I32 -> 0.12655409 | W32: =(K32-J32)/J32 -> 0.03508483

Sheet Scenario 1
C3: Scenario 1: Perpetuity
C5: Looking for the…
C7: Present Value
C9: (Constant) Cash Flow | D9: ='Appendix 3'!E32 -> 250.1
C10: Discount Rate | D10: 0.1
C12: Present Value | D12: =D9/D10 -> 2501

Sheet Scenario 2
C3: Scenario 2: Growing Perpetuity
C5: Looking for the…
C7: Present Value
C9: (Next) Cash Flow | D9: ='Appendix 3'!E32*(1+'Scenario 2'!D11) -> 257.603
C10: Discount Rate | D10: 0.1
C11: Growth Rate | D11: 0.03
C13: Present Value | D13: =D9/(D10-D11) -> 3680.0429
C15: Sensitivity Analysis
C17: =C11 -> Growth Rate | D17: =D13 -> 3680.0429
C18: 0.03 | D18: 3680.0429
C19: 0.035 | D19: 3982.3615
C20: 0.04 | D20: 4335.0667
C21: 0.045 | D21: 4751.9
C22: 0.05 | D22: 5252.1

Sheet Scenario 3
C3: Scenario 3: Annuity
C5: Looking for the…
C7: Present Value
C9: (Constant) Cash Flow | D9: ='Appendix 3'!E32 -> 250.1
C10: Discount Rate | D10: 0.1
C11: Number of Periods | D11: 20
C13: Present Value | D13: =-PV(D10,D11,D9) -> 2129.2423

Sheet Scenario 4
C3: Scenario 4: Growing Annuity
C5: Looking for the…
C7: Present Value
C9: (Next) Cash Flow | D9: ='Appendix 3'!E32*(1+'Scenario 4'!D11) -> 257.603
C10: Discount Rate | D10: 0.1
C11: Growth Rate | D11: 0.03
C12: Number of Periods | D12: 20
C14: Present Value | D14: =(D9/(D10-D11))*(1-((1+D11)/(1+D10))^D12) -> 2692.0731
C16: Sensitivity Analysis
C18: =C11 -> Growth Rate | D18: =D14 -> 2692.0731
C19: 0.03 | D19: 2692.0731
C20: 0.035 | D20: 2804.5007
C21: 0.04 | D21: 2923.1507
C22: 0.045 | D22: 3048.4107
C23: 0.05 | D23: 3180.6938

Sheet Scenario 5
C3: Scenario 5
C5: Present Value
C7: Growth Rate | D7: 0.01
C8: Cost of capital | D8: 0.1
C10: Year | D10: Time | E10: FCF | G10: Year | H10: Time | I10: FCF
C11: 2013 | D11: 1 | E11: ='Appendix 3'!G32 -> 396.3 | G11: 2013 | H11: 1 | I11: =E11 -> 396.3
C12: 2014 | D12: 2 | E12: ='Appendix 3'!H32 -> 465.2 | G12: 2014 | H12: 2 | I12: =E12 -> 465.2
C13: 2015 | D13: 3 | E13: ='Appendix 3'!I32 -> 538.9 | G13: 2015 | H13: 3 | I13: =E13 -> 538.9
C14: 2016 | D14: 4 | E14: ='Appendix 3'!J32 -> 607.1 | G14: 2016 | H14: 4 | I14: =E14 -> 607.1
C15: 2017 | D15: 5 | E15: ='Appendix 3'!K32 -> 628.4 | G15: 2017 | H15: 5 | I15: =E15+E16 -> 7680.4444
C16: Continuing Value | D16: 5 | E16: =E15*(1+D7)/(D8-D7) -> 7052.0444
C18: Present Value | I18: =NPV(D8,I11:I15) -> 6333.2283
C20: Sensitivity Analyses
C22: Growth rate | D22: =I18 -> 6333.2283
C23: 0.01 | D23: 6333.2283
C24: 0.015 | D24: 6613.7549
C25: 0.02 | D25: 6929.3472
C26: 0.025 | D26: 7287.0186
C27: 0.03 | D27: 7695.7859
C29: Cost of Capital | D29: =I18 -> 6333.2283
C30: 0.09 | D30: 7166.0222
C31: 0.095 | D31: 6724.978
C32: 0.1 | D32: 6333.2283
C33: 0.105 | D33: 5982.984
C34: 0.11 | D34: 5668.0138
C36: Growth Rate and Cost of Capital
C37: =I18 -> 6333.2283 | D37: 0.01 | E37: 0.015 | F37: 0.02 | G37: 0.025 | H37: 0.03
C38: 0.09 | D38: 7166.0222 | E38: 7537.0008 | F38: 7960.9765 | G38: 8450.1791 | H38: 9020.9155
C39: 0.095 | D39: 6724.978 | E39: 7046.3742 | F39: 7410.6233 | G39: 7826.9079 | H39: 8307.2364
C40: 0.1 | D40: 6333.2283 | E40: 6613.7549 | F40: 6929.3472 | G40: 7287.0186 | H40: 7695.7859
C41: 0.105 | D41: 5982.984 | E41: 6229.4692 | F41: 6504.9528 | G41: 6814.8717 | H41: 7166.1132
C42: 0.11 | D42: 5668.0138 | E42: 5885.8804 | F42: 6127.9544 | G42: 6398.5077 | H42: 6702.8802
